{
  "Category": "Novelas",
  "SubCategory": "Dramas (coreanos, turcos, etc.)",
  "Label": "EL POZO - ÇUKUR",
  "Images": [
    "ukur-el-nino-0.webp"
  ],
  "Description": "Çukur es una de las series turcas más populares de acción y drama criminal. Ambientada en el barrio de Çukur en Estambul, la trama gira en torno a la familia Koçovalı, que controla la zona y se enfrenta a bandas rivales, traiciones y conflictos internos. La historia mezcla violencia, lealtad y amor, mostrando cómo la vida en el barrio está marcada por códigos de honor y supervivencia.",
  "Price": "312.00",
  "Features": [
    "Episodios: 156",
    "Título original: Çukur",
    "Año: 2017–2021",
    "País: Turquía"
  ],
  "Type": "episode",
  "Episodes": 156,
  "PricePerEpisode": "2.00",
  "Date": "2026-07-15T02:01:26.561Z",
  "Update": "2026-07-15T02:01:26.561Z"
}