{
  "Category": "Novelas",
  "SubCategory": "Dramas (coreanos, turcos, etc.)",
  "Label": "FATMAGÜL - FATMAGÜL'ÜN SUÇU NE",
  "Images": [
    "fatmagul-fatmagulun-suu-ne-0.webp",
    "fatmagul-fatmagulun-suu-ne-1.webp"
  ],
  "Description": "Fatmagül es una joven humilde que sueña con casarse con su prometido Mustafa. Sin embargo, su vida cambia drásticamente tras ser víctima de una agresión por parte de cuatro hombres, entre ellos Kerim. Aunque Kerim no participó directamente, es obligado a casarse con ella para encubrir el crimen. La serie narra la lucha de Fatmagül por la justicia, su proceso de sanación y la compleja relación que surge entre ella y Kerim.",
  "Price": "162.00",
  "Features": [
    "Episodios: 81",
    "Título original: Fatmagül’ün Suçu Ne?",
    "Año: 2010–2012",
    "País: Turquía"
  ],
  "Type": "episode",
  "Episodes": 81,
  "PricePerEpisode": "2.00",
  "Date": "2026-07-16T11:57:51.904Z",
  "Update": "2026-07-16T11:57:51.904Z"
}