{
  "Category": "Novelas",
  "SubCategory": "Dramas (coreanos, turcos, etc.)",
  "Label": "GRANDES MENTIRAS - BÜYÜK YALANLAR",
  "Images": [
    "grandes-mentiras-buyuk-yalanlar-0.webp",
    "grandes-mentiras-buyuk-yalanlar-1.webp"
  ],
  "Description": "Sinopsis no disponible",
  "Price": "74.00",
  "Features": [
    "Episodios: 37",
    "Título original: Büyük Yalanlar"
  ],
  "Type": "episode",
  "Episodes": 37,
  "PricePerEpisode": "2.00",
  "Date": "2026-07-11T01:33:51.666Z",
  "Update": "2026-07-11T01:33:51.666Z"
}