{
  "Category": "Novelas",
  "SubCategory": "Dramas (coreanos, turcos, etc.)",
  "Label": "HERIDA DEL CORAZÓN - KALP YARASI",
  "Images": [
    "herida-del-corazon-kalp-yarasi-0.webp",
    "herida-del-corazon-kalp-yarasi-1.webp"
  ],
  "Description": "Sinopsis no disponible",
  "Price": "214.00",
  "Features": [
    "Episodios: 107",
    "Título original: Kalp Yarasi"
  ],
  "Type": "episode",
  "Episodes": 107,
  "PricePerEpisode": "2.00",
  "Date": "2026-07-15T02:15:07.597Z",
  "Update": "2026-07-15T02:15:07.597Z"
}